owntracks/__init__.py
owntracks/admin.py
owntracks/apps.py
owntracks/models.py
owntracks/signals.py
owntracks/tasks.py
owntracks/urls.py
owntracks/views.py
owntracks/migrations/0001_initial.py
owntracks/migrations/__init__.py
owntracks/standalone/__init__.py
owntracks/standalone/asgi.py
owntracks/standalone/celery.py
owntracks/standalone/manage.py
owntracks/standalone/settings.py
owntracks/standalone/urls.py
owntracks/standalone/wsgi.py
owntracks/tests/__init__.py
owntracks/tests/test_tasks.py
django_owntracks-0.1.0.dist-info/METADATA
django_owntracks-0.1.0.dist-info/WHEEL
django_owntracks-0.1.0.dist-info/entry_points.txt
django_owntracks-0.1.0.dist-info/top_level.txt
django_owntracks-0.1.0.dist-info/RECORD
