Metadata-Version: 2.1
Name: django-owntracks
Version: 0.1.0
Summary: Support for Owntracks
Home-page: https://github.com/kfdm/django-owntracks
Author: Paul Traylor
License: MIT License
Project-URL: Source, https://github.com/kfdm/django-owntracks
Project-URL: Tracker, https://github.com/kfdm/django-owntracks/issues
Classifier: Environment :: Web Environment
Classifier: Framework :: Django
Classifier: Intended Audience :: Developers
Classifier: License :: OSI Approved :: MIT License
Classifier: Operating System :: OS Independent
Classifier: Programming Language :: Python
Classifier: Programming Language :: Python :: 3
Classifier: Programming Language :: Python :: 3 :: Only
Classifier: Programming Language :: Python :: 3.6
Classifier: Programming Language :: Python :: 3.7
Classifier: Programming Language :: Python :: 3.8
Classifier: Programming Language :: Python :: 3.9
Classifier: Programming Language :: Python :: 3.10
Classifier: Topic :: Internet :: WWW/HTTP
Classifier: Topic :: Internet :: WWW/HTTP :: Dynamic Content
Requires-Python: >=3.6
Requires-Dist: celery
Requires-Dist: django-mqtt
Requires-Dist: Django (>=3.2)
Requires-Dist: qrcode
Provides-Extra: dev
Requires-Dist: black ; extra == 'dev'
Requires-Dist: flake8 ; extra == 'dev'
Requires-Dist: psycopg2-binary ; extra == 'dev'
Provides-Extra: standalone
Requires-Dist: celery ; extra == 'standalone'
Requires-Dist: django-environ ; extra == 'standalone'
Requires-Dist: redis ; extra == 'standalone'
